{
	"configurations" : 
	[
		{
			"directories" : 
			[
				{
					"build" : ".",
					"jsonFile" : "directory-.-Debug-d0094a50bb2071803777.json",
					"minimumCMakeVersion" : 
					{
						"string" : "3.23"
					},
					"projectIndex" : 0,
					"source" : ".",
					"targetIndexes" : 
					[
						0,
						1
					]
				}
			],
			"name" : "Debug",
			"projects" : 
			[
				{
					"directoryIndexes" : 
					[
						0
					],
					"name" : "cn_project",
					"targetIndexes" : 
					[
						0,
						1
					]
				}
			],
			"targets" : 
			[
				{
					"directoryIndex" : 0,
					"id" : "receive::@6890427a1f51a3e7e1df",
					"jsonFile" : "target-receive-Debug-fb22502bc4cb3810dfe1.json",
					"name" : "receive",
					"projectIndex" : 0
				},
				{
					"directoryIndex" : 0,
					"id" : "send::@6890427a1f51a3e7e1df",
					"jsonFile" : "target-send-Debug-5e0e80a16d723042cc23.json",
					"name" : "send",
					"projectIndex" : 0
				}
			]
		}
	],
	"kind" : "codemodel",
	"paths" : 
	{
		"build" : "C:/Users/23256/Desktop/cn_project/cmake-build-debug",
		"source" : "C:/Users/23256/Desktop/cn_project"
	},
	"version" : 
	{
		"major" : 2,
		"minor" : 4
	}
}
